{
    "name": "Human",
    "description": "Found throughout the multiverse, humans are as varied as they are numerous, and they endeavor to achieve as much as they can in the years they are given. Their ambition and resourcefulness are commended, respected, and feared on many worlds.",
    "source": "PHB",
    "source_page": 0,
    "creature_type": "Humanoid",
    "age": {
        "lifespan": "less than 100 years"
    },
    "size": {
        "category": "Medium (about 4-7 feet tall) or Small (about 2-4 feet tall)",
        "choice_required": true,
        "options": ["Medium", "Small"]
    },
    "speed": {
        "walk": 30
    },
    "traits": [
        {
            "name": "Resourceful",
            "description": "You gain Heroic Inspiration whenever you finish a Long Rest.",
            "grants": {
                "heroic_inspiration": "on Long Rest"
            }
        },
        {
            "name": "Skillful",
            "description": "You gain proficiency in one skill of your choice.",
            "choice_required": true,
            "grants": {
                "skill_proficiencies": "one skill of choice"
            }
        },
        {
            "name": "Versatile",
            "description": "You gain an Origin feat of your choice (see chapter 5). Skilled is recommended.",
            "grants": {
                "origin_feat": "one of choice (Skilled recommended)"
            }
        }
    ],
    "version": "5.5E"
} 